MANIFEST.in
README
setup.py
cheffy/__init__.py
cheffy/auth.py
cheffy/client.py
cheffy/rsa.py
cheffy.egg-info/PKG-INFO
cheffy.egg-info/SOURCES.txt
cheffy.egg-info/dependency_links.txt
cheffy.egg-info/requires.txt
cheffy.egg-info/top_level.txt
debian/changelog
debian/compat
debian/control
debian/copyright
debian/rules