Metadata-Version: 1.0
Name: cheffy
Version: 0.3.8
Summary: A simple requests based wrapper for a Chef server api.
Home-page: https://pypi.python.org/pypi/cheffy
Author: Roman Dashevsky
Author-email: dashevsky@selectel.ru
License: LICENSE
Platform: UNKNOWN
